cleangram_codegen/__init__.py
cleangram_codegen/__main__.py
cleangram_codegen/_version.py
cleangram_codegen/cli.py
cleangram_codegen/comps.py
cleangram_codegen/const.py
cleangram_codegen/enums.py
cleangram_codegen/generator.py
cleangram_codegen/models.py
cleangram_codegen/parser.py
cleangram_codegen/templates.py
cleangram_codegen/util.py
cleangram_codegen-0.0.0.dev3.dist-info/WHEEL
cleangram_codegen-0.0.0.dev3.dist-info/METADATA
cleangram_codegen-0.0.0.dev3.dist-info/RECORD
