Metadata-Version: 2.1
Name: cleangram-codegen
Version: 0.0.0.dev3
Summary: Code generator for cleangram
Author: Arwichok
Author-email: me@arwi.dev
Requires-Python: >=3.8,<4.0
Classifier: Programming Language :: Python :: 3
Classifier: Programming Language :: Python :: 3.10
Classifier: Programming Language :: Python :: 3.8
Classifier: Programming Language :: Python :: 3.9
Requires-Dist: beautifulsoup4 (>=4.11.1,<5.0.0)
Requires-Dist: black (>=22.3.0,<23.0.0)
Requires-Dist: flake8 (>=4.0.1,<5.0.0)
Requires-Dist: httpx
Requires-Dist: isort (>=5.10.1,<6.0.0)
Requires-Dist: mypy (>=0.961,<0.962)
Requires-Dist: pydantic (>=1.9.1,<2.0.0)
Requires-Dist: typer (>=0.4.1,<0.5.0)
